{
    "20230408": [
        {
            "sets": [
                {
                    "weight": 225,
                    "reps": 5
                },
                {
                    "weight": 235,
                    "reps": 5
                },
                {
                    "weight": 245,
                    "reps": 5
                },
                {
                    "weight": 245,
                    "reps": 3
                }
            ],
            "rests": [
                5,
                5,
                5
            ],
            "name": "squat"
        }
    ]
}